{
    "user": {
        "id": "6480831590",
        "nickname": "麦卡PU10P",
        "gender": "男",
        "location": "其他",
        "birthday": "白羊座",
        "description": "让我用不字造句，我只会写出来绝不绝不",
        "verified_reason": "微博剪辑视频博主",
        "talent": "",
        "education": "复旦大学",
        "work": "",
        "weibo_num": 10162,
        "following": 996,
        "followers": 166000
    },
    "weibo": [
        {
            "id": "P1YorcjhL",
            "user_id": "",
            "content": "看了三联对南京那位火车机械师被撞身亡的事件的报道，再次感叹深度报道有多必要，如果没有这篇报道，人们只会知道是野猪的问题，对背后涉及铁路规定、流程的多处不合理并且同样构成行车安全隐患的问题，就会一无所知。1）随车机械师工作量很大，尤其是最近两三年评分系统越收越紧，新增了几十项业内人士无法理解的扣钱项目，精神压力很大。（想起东航事件后的一个网贴，也提到了类似的现象）2）流程上，司机和机械师分属不同部门，出事后协调和看护无法落实；3）最令人无法理解的是，乘客都看见了，出事后撞人列车的机械师却没有找到被撞的人，撞到野猪停车的那列车机械师没回来，两辆车居然都直接走了……直到后来的车次司机发现异常停车，距离出事已过去一个多小时。死者并没有受到直接撞击，更像是剐蹭，也就是说，人本来完全是有可能救回来的。4）根据《铁路交通事故调查处理规则》规定，繁忙干线行车中断1小时以上和造成1人死亡相同，均属于B类事故。细思极恐。不是说一定是因为这条规定就放弃找人，但这规定客观上就是把人命的排序放在了列车准点率的同等甚至更靠后的位置。顺便感叹下原帖评论里一堆“机械师自己侵限另一边的线路”“铁路晚点怎么不重要了？有时候迟到的影响非常严重”乃至滑坡到“全国铁路晚点什么后果08年雪灾的事情那么快就忘了？”真是温良又自觉的维稳最小单位。http://t.cn/A6m2eQ1A ",
            "article_url": "",
            "original_pictures": "无",
            "retweet_pictures": null,
            "original": true,
            "video_url": "无",
            "publish_place": "无",
            "publish_time": "2024-11-25 21:05",
            "publish_tool": "微博网页版",
            "up_num": 252,
            "retweet_num": 148,
            "comment_num": 2
        },
        {
            "id": "P1VfIs8uV",
            "user_id": "",
            "content": "我是看完电影才知道演小孩儿的曾慕梅是梅婷的女儿（虽然一直觉得眼熟）。等她这一代女孩儿长大，再遇到冯远征演的那种家暴男，应该就会是另一个故事了。她的黑眼圈是天生的，不会是被打的。  ",
            "article_url": "",
            "original_pictures": "无",
            "retweet_pictures": null,
            "original": true,
            "video_url": "无",
            "publish_place": "无",
            "publish_time": "2024-11-25 13:05",
            "publish_tool": "HarmonyOS设备",
            "up_num": 74,
            "retweet_num": 2,
            "comment_num": 7
        },
        {
            "id": "P1UrpvTpB",
            "user_id": "",
            "content": "货拉拉司机和保时捷工作人员的纠纷，其实是挺典型的货拉拉式纠纷。什么意思呢？就是货拉拉除了平台app上的接单之外，其实还默认司机是可以在线下通过细化和增加劳动，和乘客谈价的，这有现实考量，因为送货的情况很复杂，的确可能产生各种无法提前列明的事项（比如这起里就是从三楼把货物搬到一楼并摆放齐整），也可以让司机获得额外的收入，同时更重要的是单价定得低可以吸引更多用户，同时通过司机可以线下加钱（以弥补平台服务价格的低廉）的潜规则，把风险转嫁到司机和乘客，出现纠纷平台可以免责。这起事件里估计就是保时捷工作人员和司机谈了附加劳动的费用，但后来发现无法开票，需要自掏腰包，于是就反悔了。保时捷工作人员不该出尔反尔，在矛盾激化过程中应当承担主要责任。但货拉拉把私下议价变成一种潜规则，自己置身事外，其实也制造了大量纠纷甚至安全隐患。我想起前几年著名的那起货拉拉司机和一位女士夜里在车上发生争吵，后者在恐惧中跳车身亡。司机以过失致人死亡罪判一缓一，事情本身的讨论已经很多就不赘述了，当时车上发生的争吵乃至司机的威胁到底是什么程度，现在也不可考了，判一缓一其实是很轻的量刑了。想到这件事是因为让我印象很深的一点：司机和女乘客的矛盾，其实在司机等候的时候就已经在酝酿了，女乘客当时在搬家，司机提出帮她搬（大概率是要收费的），但女乘客坚持自己一件一件搬下楼。是否超出规定的司机等候的时间，超出的部分有没有按规定支付费用，这些应该都在平台的规定范围内有章可循，问题不大，但是没让司机赚到那笔外快，就成了后面那场悲剧的重要诱因。#货拉拉 保时捷##货拉拉司机回应保时捷# 原图 ",
            "article_url": "",
            "original_pictures": "https://wx4.sinaimg.cn/large/0074AUlMgy1hvyaz67nzgj30j60q7h43.jpg",
            "retweet_pictures": null,
            "original": true,
            "video_url": "无",
            "publish_place": "无",
            "publish_time": "2024-11-25 11:01",
            "publish_tool": "微博网页版",
            "up_num": 60,
            "retweet_num": 8,
            "comment_num": 5
        },
        {
            "id": "P1KAikv5e",
            "user_id": "",
            "content": "品客女权和男拳incel的三次大战第一次：胖猫事件通告出来，相信警方通报（两人是正常经济往来，没捞）VS不相信警方通报，“拳塔一体实锤”第二次：黑神话悟空主美多年前的（）言论被扒出，“这种反贼言论没有追溯期”VS“支持国产A3大作，弘扬中华传统文化，不要破坏舆论环境，先搁置争议”第三次：体操前冠军转型性感主播，被小她十岁的前奥运冠军在评论区DISS“别给体操扣屎盆子”，“代表国家的运动员退役后应该注意形象，不是什么活都能接”VS“这就鉴擦上了？给兄弟们免费福利的女性得保护好，这关爱国什么事？反对道德绑架！”#管晨辰 吴柳芳##前体操冠军吴柳芳擦边争议后发声##吴柳芳涨粉# ",
            "article_url": "",
            "original_pictures": "无",
            "retweet_pictures": null,
            "original": true,
            "video_url": "无",
            "publish_place": "无",
            "publish_time": "2024-11-24 09:56",
            "publish_tool": "微博网页版",
            "up_num": 743,
            "retweet_num": 19,
            "comment_num": 44
        },
        {
            "id": "P1GnKDqEp",
            "user_id": "",
            "content": "一个在豆瓣上没名字的电影节颁了三个大奖给两部在豆瓣上没名字的电影的主创。  ",
            "article_url": "",
            "original_pictures": "无",
            "retweet_pictures": null,
            "original": true,
            "video_url": "无",
            "publish_place": "无",
            "publish_time": "2024-11-23 23:14",
            "publish_tool": "无",
            "up_num": 437,
            "retweet_num": 41,
            "comment_num": 16
        },
        {
            "id": "P1ESb1zb1",
            "user_id": "",
            "content": "远洋捕捞这个词用在公权力异地执法抓捕企业家这种事情上真的太传神也太恶心了，是趋利性执法（这个词所对应的行为也很恶心）发展到next level的产物。  ",
            "article_url": "",
            "original_pictures": "无",
            "retweet_pictures": null,
            "original": true,
            "video_url": "无",
            "publish_place": "无",
            "publish_time": "2024-11-23 19:23",
            "publish_tool": "微博网页版",
            "up_num": 188,
            "retweet_num": 18,
            "comment_num": 9
        },
        {
            "id": "P1DlBhU7T",
            "user_id": "",
            "content": "#微信将14天后自动清理原图原视频# 这个tag给我看晕了。微信不是一直这样吗？还是说以后这个“清理”是真的清理，能把空间腾出来，而过去的清理只是无法显示，实际上该占多少空间还是占多少空间？如果是这样，实际上这个标签应该这样写：“微信修复14天自动清理原图原视频但依然占据存储空间的bug”。而实际上是增加了一个开关，可以让用户自主选择“是否14天后自动清理原图原视频”。 ",
            "article_url": "",
            "original_pictures": "无",
            "retweet_pictures": null,
            "original": true,
            "video_url": "无",
            "publish_place": "无",
            "publish_time": "2024-11-23 15:30",
            "publish_tool": "微博网页版",
            "up_num": 41,
            "retweet_num": 4,
            "comment_num": 5
        },
        {
            "id": "P1C17iAs3",
            "user_id": "",
            "content": "赵又廷本来要演胡医生的，他自己看了剧本以后挑了前夫哥。有眼光的。贡献了全片最有喜感的一个角色。吃饭那场戏给我笑疯了，调度也好，甚至有一种动作喜剧片的感觉。另外看到很多演员收到剧本都婉拒了出演，可能对题材有顾虑。类似的顾虑也出现在《出走的决心》选角时，丈夫角色一度无人肯接，直到姜武。女性主创的电影还是要多多支持，天然的障碍类型就比其他电影多。 原图 ",
            "article_url": "",
            "original_pictures": "https://wx3.sinaimg.cn/large/0074AUlMgy1hvw1fzqh1lj30u00z4tbr.jpg",
            "retweet_pictures": null,
            "original": true,
            "video_url": "无",
            "publish_place": "无",
            "publish_time": "2024-11-23 12:07",
            "publish_tool": "无",
            "up_num": 4288,
            "retweet_num": 175,
            "comment_num": 97
        },
        {
            "id": "P1vP5j2ut",
            "user_id": "",
            "content": "根据你所看到的我的微博发言，我的赛博MBTI最可能是哪种？ 根据你所看到的我的微博发言，我的赛博MBTI最可能是哪种？  ",
            "article_url": "",
            "original_pictures": "无",
            "retweet_pictures": null,
            "original": true,
            "video_url": "无",
            "publish_place": "无",
            "publish_time": "2024-11-22 20:21",
            "publish_tool": "微博网页版",
            "up_num": 73,
            "retweet_num": 1,
            "comment_num": 12
        },
        {
            "id": "P1nx0lKim",
            "user_id": "",
            "content": "如果这种来自侵略者的威胁不奏效，人类可能毁灭。如果这种来自侵略者的威胁奏效了，人类应该毁灭。  ",
            "article_url": "",
            "original_pictures": "无",
            "retweet_pictures": null,
            "original": true,
            "video_url": "无",
            "publish_place": "无",
            "publish_time": "2024-11-21 23:15",
            "publish_tool": "无",
            "up_num": 51,
            "retweet_num": 7,
            "comment_num": 1
        },
        {
            "id": "P19iytDUI",
            "user_id": "",
            "content": "浙大学阀子弟轻取竺可桢奖被质疑（图一），没想到评论区一大群学术牛马纷纷表示“可以接受”“可以理解”“人和人起点是不一样”“只要真实参与了就没问题”，真太好孝了。随手点开一位（图二）发现被我提前拉黑了。这我就有兴趣了。解除拉黑一搜，果然它对姜萍骂了一路，不但对王闰秋、阿里和央视大得多的责任只字不提，甚至还把她和徐州董畜相提并论。多公平啊！#一些样本# #标记重捕法# [组图共5张] 原图 ",
            "article_url": "",
            "original_pictures": "https://ww1.sinaimg.cn/large/0074AUlMgy1hvsir9skeij30u08t3b29.jpg,https://ww4.sinaimg.cn/large/0074AUlMgy1hvsiracavej30ku085dgp.jpg,https://ww2.sinaimg.cn/large/0074AUlMgy1hvsirano81j30ku07d0ts.jpg,https://ww2.sinaimg.cn/large/0074AUlMgy1hvsirazgc2j30ku06kmxn.jpg,https://ww4.sinaimg.cn/large/0074AUlMgy1hvsirbdakzj30ku06cq3o.jpg",
            "retweet_pictures": null,
            "original": true,
            "video_url": "无",
            "publish_place": "无",
            "publish_time": "2024-11-20 11:01",
            "publish_tool": "无",
            "up_num": 329,
            "retweet_num": 50,
            "comment_num": 9
        },
        {
            "id": "P198NuDUU",
            "user_id": "",
            "content": "不知道大家有没有印象，一个叫小尧的人气美食博主突然就停更了很久，后来虽然复出了，但更新频率很低，变成一年一更了。于是大家就叫他年更尧。#每日烂梗#  ",
            "article_url": "",
            "original_pictures": "无",
            "retweet_pictures": null,
            "original": true,
            "video_url": "无",
            "publish_place": "无",
            "publish_time": "2024-11-20 10:36",
            "publish_tool": "无",
            "up_num": 18,
            "retweet_num": 0,
            "comment_num": 6
        },
        {
            "id": "P14ECuspE",
            "user_id": "",
            "content": "这场虽然输了，但真的没有什么槽点，反而亮点挺多。日本队18强赛第一个被对方打进的球来自中国队（第一个是乌龙球），而且这个球在任何评价标准里都是一个可以足以集锦的好球，谢文能那一漏很精彩。对日本通过地面进攻破门，而且还是这么精彩的破门，不容易的。而且国足最近几场，场场都有漂亮的运动战进球（再回味一下高准翼对印尼时的中场外脚背传球和张玉林对巴林时最后的逆转绝杀），感觉是摸到门路了，一门心思防反，把自己的技术潜力释放出来了。日本的进球有两个定位球，他们定位球演练得确实高级，但至少国足在运动战基本算防住了，作为世界排名第90名开外的球队面对世界排名第15的球队，能做到这点，没法要求太苛刻。这组接下来是真的够乱的，连印尼都在沙特身上拿到了首胜，这支沙特完全是亚洲二流了，明年的下一场就是对沙特，希望国足最近一段时间的稳定性能延续下去。#国足VS日本#[查看全部图片/视频] ",
            "article_url": "",
            "original_pictures": "无",
            "retweet_pictures": null,
            "original": true,
            "video_url": "无",
            "publish_place": "无",
            "publish_time": "2024-11-19 23:11",
            "publish_tool": "微博视频号",
            "up_num": 28,
            "retweet_num": 0,
            "comment_num": 11
        },
        {
            "id": "P0TIajKqV",
            "user_id": "",
            "content": "忽然发现黄直中几乎就是老白男的下联。  ",
            "article_url": "",
            "original_pictures": "无",
            "retweet_pictures": null,
            "original": true,
            "video_url": "无",
            "publish_place": "无",
            "publish_time": "2024-11-18 19:20",
            "publish_tool": "无",
            "up_num": 457,
            "retweet_num": 65,
            "comment_num": 14
        },
        {
            "id": "P0KxKAU9k",
            "user_id": "",
            "content": "吃了顿模仿怀石料理的中式素食，每道菜都摆盘摆得跟个庭院似的。我大开眼界。整顿饭我说得最多的一句话是：“这个能吃吗？”（答案有1/3是不能吃，果然人还是要多不懂就问）  ",
            "article_url": "",
            "original_pictures": "无",
            "retweet_pictures": null,
            "original": true,
            "video_url": "无",
            "publish_place": "无",
            "publish_time": "2024-11-17 19:59",
            "publish_tool": "微博网页版",
            "up_num": 38,
            "retweet_num": 1,
            "comment_num": 15
        },
        {
            "id": "P0CVDcLhQ",
            "user_id": "",
            "content": "无差别犯罪的无差别仅指行凶者和受害者个体没有关联，很多时候行凶者选择伤害对象时是有差别的。找到这种差别，寻找这种差别产生的原因，或许可以在一定程度上预防类似的犯罪。很多人说不要听杀人犯背后的故事，我理解也部分认同，但大众可以不听，有关部门应该听，必须听。相信已经在听了。社交媒体时代，罪犯的行为很可能是多因一果的，除了罪犯嘴上说的那些，还要多看看它们加了哪些群，平时上哪些网站，关注了哪些人并有频繁互动。这些都很容易查。有些也许是耦合，有些却可能是犯罪的潜在推手，相信有关部门一定有细察明辨两者区别的能力，找到给这些语言和恶意提供孵化的地方和人，切断它们的联结。另外我当然认同无差别犯罪会有模仿效应，但要减少模仿，除了减少恶性事件发生后对细节的渲染和传播，还有必要做前述的这些调查，因为有些模仿，是早在案件发生之前就在语言层面开始的，而不是案件发生之后。 ",
            "article_url": "",
            "original_pictures": "无",
            "retweet_pictures": null,
            "original": true,
            "video_url": "无",
            "publish_place": "无",
            "publish_time": "2024-11-17 00:36",
            "publish_tool": "微博网页版",
            "up_num": 911,
            "retweet_num": 116,
            "comment_num": 32
        },
        {
            "id": "P0sH0nHeY",
            "user_id": "",
            "content": "川普二期还没来，我已经开始觉得苏联笑话不香了。  ",
            "article_url": "",
            "original_pictures": "无",
            "retweet_pictures": null,
            "original": true,
            "video_url": "无",
            "publish_place": "无",
            "publish_time": "2024-11-15 22:33",
            "publish_tool": "无",
            "up_num": 90,
            "retweet_num": 3,
            "comment_num": 7
        },
        {
            "id": "P0shv7Bhc",
            "user_id": "",
            "content": "说一句话承认自己从来没看过这一季再见爱人，一直在云评论。比如我至今不知道是李xing亮还是李hang亮。  ",
            "article_url": "",
            "original_pictures": "无",
            "retweet_pictures": null,
            "original": true,
            "video_url": "无",
            "publish_place": "无",
            "publish_time": "2024-11-15 21:30",
            "publish_tool": "HarmonyOS设备",
            "up_num": 227,
            "retweet_num": 5,
            "comment_num": 26
        },
        {
            "id": "P0owCekZz",
            "user_id": "",
            "content": "盘尼西林say say it again下面的热评，9万赞。点进去翻了一分钟没有一个人觉得这句话有（不止一个）问题。经提醒发现是2017年的热评，也许现在发就不会是这么一边倒的盛况了吧。#一些样本#  原图 ",
            "article_url": "",
            "original_pictures": "https://wx2.sinaimg.cn/large/0074AUlMgy1hvmsa0ysf5j30ku07bq3a.jpg",
            "retweet_pictures": null,
            "original": true,
            "video_url": "无",
            "publish_place": "无",
            "publish_time": "2024-11-15 11:56",
            "publish_tool": "无",
            "up_num": 3465,
            "retweet_num": 303,
            "comment_num": 66
        },
        {
            "id": "P0fJZjDF5",
            "user_id": "",
            "content": "胖哥李小鹿，简中网络世界的怪物猎人。  ",
            "article_url": "",
            "original_pictures": "无",
            "retweet_pictures": null,
            "original": true,
            "video_url": "无",
            "publish_place": "无",
            "publish_time": "2024-11-14 13:34",
            "publish_tool": "无",
            "up_num": 451,
            "retweet_num": 25,
            "comment_num": 16
        },
        {
            "id": "P0fvD9woS",
            "user_id": "",
            "content": "在川普任期最后一年赶去美国抄底移民政策结果遇上万斯当选的@加州男大985 be like：  原图 ",
            "article_url": "",
            "original_pictures": "https://wx4.sinaimg.cn/large/0074AUlMgy1hvlohjxhnrg30cf06vqv6.gif",
            "retweet_pictures": null,
            "original": true,
            "video_url": "无",
            "publish_place": "无",
            "publish_time": "2024-11-14 12:59",
            "publish_tool": "微博网页版",
            "up_num": 27,
            "retweet_num": 3,
            "comment_num": 2
        },
        {
            "id": "P0atb0TZK",
            "user_id": "",
            "content": "希望43位伤者都能平安，都不被下一个热点冲刷、遗忘。  ",
            "article_url": "",
            "original_pictures": "无",
            "retweet_pictures": null,
            "original": true,
            "video_url": "无",
            "publish_place": "无",
            "publish_time": "2024-11-14 00:09",
            "publish_tool": "微博网页版",
            "up_num": 164,
            "retweet_num": 5,
            "comment_num": 2
        },
        {
            "id": "P07OSm1Nw",
            "user_id": "",
            "content": "关于那份流传甚广的判决书，刚发现昨天的提醒原来早就被夹了。这个判决书有可能是个脏弹，要小心。年龄对不上，判决书上的樊某是61岁。到时候拿这颗脏弹说你们转发不实信息。它们言之凿凿造谣和为恐怖分子叫好只禁言30天，你转个判决书就算说”真假不知“都可能被炸。  ",
            "article_url": "",
            "original_pictures": "无",
            "retweet_pictures": null,
            "original": true,
            "video_url": "无",
            "publish_place": "无",
            "publish_time": "2024-11-13 17:24",
            "publish_tool": "微博网页版",
            "up_num": 286,
            "retweet_num": 15,
            "comment_num": 6
        },
        {
            "id": "P01rijrCh",
            "user_id": "",
            "content": "“偶发”可以是个简称，全称可能是“配偶引发”。  ",
            "article_url": "",
            "original_pictures": "无",
            "retweet_pictures": null,
            "original": true,
            "video_url": "无",
            "publish_place": "无",
            "publish_time": "2024-11-13 01:10",
            "publish_tool": "无",
            "up_num": 448,
            "retweet_num": 16,
            "comment_num": 14
        },
        {
            "id": "OFXmR7QIR",
            "user_id": "",
            "content": "本来发生35死的惨剧，已经是非常惨痛的公共记忆了。现在这份通报一出，无论本意为何，虽然做到了及时、透明、较为详实，相比此前类似的一些事件有积极的变化，但通报一部分内容的实际效果，间接引发了一群人在毫无根据的情况下对（包括但不限于）一位无辜女性的攻击围剿，对社会治安明晃晃的威胁，对国家法律赤裸裸的不屑。此情此景对每个有良知有常识的普通人来说，都是一种惨痛叠加惨痛、愤怒叠加愤怒的公共记忆。但我们唯独不会恐惧叠加恐惧。该恐惧的永远是那些畜生。 ",
            "article_url": "",
            "original_pictures": "无",
            "retweet_pictures": null,
            "original": true,
            "video_url": "无",
            "publish_place": "无",
            "publish_time": "2024-11-12 21:16",
            "publish_tool": "微博网页版",
            "up_num": 896,
            "retweet_num": 114,
            "comment_num": 11
        },
        {
            "id": "OFWDp1s2n",
            "user_id": "",
            "content": "请大家把涉及恶意引导的帖子截图私信给我。  ",
            "article_url": "",
            "original_pictures": "无",
            "retweet_pictures": null,
            "original": true,
            "video_url": "无",
            "publish_place": "无",
            "publish_time": "2024-11-12 19:24",
            "publish_tool": "无",
            "up_num": 238,
            "retweet_num": 16,
            "comment_num": 29
        },
        {
            "id": "OFWzYeYOs",
            "user_id": "",
            "content": "好吧，已经被系统强行设置为仅自己可见了。懂了。  ",
            "article_url": "",
            "original_pictures": "无",
            "retweet_pictures": null,
            "original": true,
            "video_url": "无",
            "publish_place": "无",
            "publish_time": "2024-11-12 19:16",
            "publish_tool": "微博网页版",
            "up_num": 113,
            "retweet_num": 3,
            "comment_num": 20
        },
        {
            "id": "OFLwV6A4x",
            "user_id": "",
            "content": "我曾经以为很多川粉是真的因为担心自己小孩而相信那些没有出处更像都市传说的“很多孩子受了误导做了变性手术”、并因此仇视LGBT。后来发现刚好相反。他们是因为本来就仇视LGBT才会相信这些都市传说，才会拿“担心小孩的性取向”当成正当化扩大化这种仇恨的借口。仅仅因为LGBT从过去的“完全不可见”的状态更多地出现在社会视野中，对他们来说就已经足以构成巨大的冒犯。 ",
            "article_url": "",
            "original_pictures": "无",
            "retweet_pictures": null,
            "original": true,
            "video_url": "无",
            "publish_place": "无",
            "publish_time": "2024-11-11 15:08",
            "publish_tool": "微博网页版",
            "up_num": 1332,
            "retweet_num": 113,
            "comment_num": 60
        },
        {
            "id": "OFEvs2kyG",
            "user_id": "",
            "content": "一个普通人，被放置到一个复杂的环境里，被一群富有经验和主导权的人利用、出卖，那群人赚得盆满钵满，就算有争议也不用付出任何代价，而她却成为景观、“骗子”、“疯子”，被不断地审判批判嘲讽羞辱，成为最大甚至是唯一的受害者。她们也根本没得到什么好处，一个本来也不可能靠数学比赛真的进好大学，另一个就算收获了流量，作为素人也只会让她的明星丈夫（和整个节目）获益。作为观众的大多数人根本不会体察其中权力关系的严重不对等，而就算告诉他们这一点，他们也不会对她们生出什么怜悯之心，而只会说“既然她们做出了选择，那就要承受代价”。刚才播放到乔治哈里森的名曲while my guitar gently weeps，歌词像极了姜萍和麦琳处境的写照：I don't know how someone controlled youThey bought and sold you.I look at the world and I notice it's turningWhile my guitar gently weeps.I don't know how you were divertedYou were perverted tooI don't know how you were invertedNo one alerted you.I look from the wings at the play you are stagingWhile my guitar gently weeps.发这条就是想提醒看到这条的所有人：该死的另有其人。http://t.cn/A6nTUMap ",
            "article_url": "",
            "original_pictures": "无",
            "retweet_pictures": null,
            "original": true,
            "video_url": "无",
            "publish_place": "无",
            "publish_time": "2024-11-10 21:15",
            "publish_tool": "微博网页版",
            "up_num": 219,
            "retweet_num": 32,
            "comment_num": 3
        },
        {
            "id": "OFrqqnCVr",
            "user_id": "",
            "content": "冷知识：现任美国总统是拜登。  ",
            "article_url": "",
            "original_pictures": "无",
            "retweet_pictures": null,
            "original": true,
            "video_url": "无",
            "publish_place": "无",
            "publish_time": "2024-11-09 11:57",
            "publish_tool": "无",
            "up_num": 123,
            "retweet_num": 8,
            "comment_num": 11
        },
        {
            "id": "OFlvWfoih",
            "user_id": "",
            "content": "我过去不信八字，现在其实也不太信，但是我已经完全不排斥做八字测算了。外面的世界越动荡，越需要更多关注自身，催利避害，增加对外部负面的抗性。1、相比更像社交游戏的星座和MBTI不同的是，八字之类的命理测算更有积淀，也更有建设性，它不光提示“你是怎样的人”，也会给出建议和对策：什么时候做什么事儿会比较好？目前的困境咋解决？好运更大概率出现在哪些方面？有麦玲玲代言，诸多命理大咖提供技术支持。2、玄学当然不是科学，但人人不同，事事不同，处世之道大差不差。虽然一命二运三风水的古语见仁见智，但在我看来它更像是一门借助命理框架探索内心的工具，并不是要决定你的人生，而是提供更多可能性和辨析角度，帮助自己在思考人生时提供指引和灵感。3、第一次做八字测算，不管是什么原因，真的还挺准。比如说我有时会伤人而不自知，容易招致误会；还有十神分析说我月支伤宫，无法从事过于重复性的工作，还给出了利于发展的行业方向，刚好是我最近一年正在关注的领域。4、紫薇斗数的系统里，今年是宫位转变之年，进入九紫大运，俗称火运，正是特别适合求变的节点。当然每人命盘千差万别，也不是不需要变而硬变，有时候原地不动反而可以避开陷阱。5、八字这种老祖宗传下来的东西，准不准当然见仁见智，但其实作为一门广义上的分类学还是挺有意思的。就看它如何把人生的各种特质、维度清晰地分门别类，再构建起一整套解释系统，这种分类的逻辑思路其实也可以灵活运用到其他地方。🔗放在🍎论区了，可以给自己测一测。当然，如果你知道你喜欢的人或者讨厌的人的生辰八字，也可以给他们测一测，知己知彼 ✨另外！个人觉得一万字的一阶报告已经足够详尽了！可以保存细看，收到的短信链接可以随时点开查看，也可以发送到信箱。至于是否需要再深入咨询，看个人！客服微信不需要可以直接删掉！（记得收藏测试报告，不过可以通过链接随时找回）。Let's keep calm and 紫薇斗数，好运不怕晚。有问题也可以在评论区问。 ",
            "article_url": "",
            "original_pictures": "无",
            "retweet_pictures": null,
            "original": true,
            "video_url": "无",
            "publish_place": "无",
            "publish_time": "2024-11-08 20:54",
            "publish_tool": "微博网页版",
            "up_num": 33,
            "retweet_num": 7,
            "comment_num": 8
        },
        {
            "id": "OFhBFvxfC",
            "user_id": "",
            "content": "我不会再转发任何梗化川普的东西。想到这个是因为昨天看到王天小天王模仿川普口音的视频，惟妙惟肖非常好笑，但我转了又删了。我是这样想的：川普很多地方是很有喜感，有很大的演绎空间，很多美国艺人包括崔娃也很喜欢模仿他，但这些模仿、梗化川普的做法，在社交网络上天然地容易得到传播，客观上会让这个人显得“无害”“有趣”甚至“亲切”，而这些和真实的川普八竿子打不着。这是一种麻醉剂甚至是致幻剂，在一定程度上美化了这个人，隐藏了他的各种恶处和对世界潜在的巨大破坏力。不要拿恶人作梗。 ",
            "article_url": "",
            "original_pictures": "无",
            "retweet_pictures": null,
            "original": true,
            "video_url": "无",
            "publish_place": "无",
            "publish_time": "2024-11-08 10:57",
            "publish_tool": "微博网页版",
            "up_num": 22327,
            "retweet_num": 2962,
            "comment_num": 251
        },
        {
            "id": "OFhsv1fSS",
            "user_id": "",
            "content": "说一件“你明知道是正确的但却依然很难接受”的事情。我的是：1、蜘蛛不是昆虫。2、Radiohead不是britpop。  ",
            "article_url": "",
            "original_pictures": "无",
            "retweet_pictures": null,
            "original": true,
            "video_url": "无",
            "publish_place": "无",
            "publish_time": "2024-11-08 10:35",
            "publish_tool": "无",
            "up_num": 122,
            "retweet_num": 16,
            "comment_num": 34
        },
        {
            "id": "OFgQ5xgck",
            "user_id": "",
            "content": "如果美国大选是一个巨大的微博你以为的世界VS实际上的世界be like：  [组图共2张] 原图 ",
            "article_url": "",
            "original_pictures": "https://ww1.sinaimg.cn/large/0074AUlMgy1hvejvkx4p7j305f03tq2r.jpg,https://ww2.sinaimg.cn/large/0074AUlMgy1hvejvld5zfj305e03kdfn.jpg",
            "retweet_pictures": null,
            "original": true,
            "video_url": "无",
            "publish_place": "无",
            "publish_time": "2024-11-08 09:00",
            "publish_tool": "无",
            "up_num": 278,
            "retweet_num": 22,
            "comment_num": 8
        },
        {
            "id": "OF37AiYCy",
            "user_id": "",
            "content": "未来的世界注定动荡。只有热搜上的王楚钦无缘8强让我稍许感到了一丝宝贵的确定性。  ",
            "article_url": "",
            "original_pictures": "无",
            "retweet_pictures": null,
            "original": true,
            "video_url": "无",
            "publish_place": "无",
            "publish_time": "2024-11-06 22:05",
            "publish_tool": "微博网页版",
            "up_num": 891,
            "retweet_num": 78,
            "comment_num": 60
        },
        {
            "id": "OF16SC7dg",
            "user_id": "",
            "content": "再过几个小时，很多中国人这辈子对川普最有好感的一天就要过去了。今番良晤，豪兴不减，但日子终究要回到反美的正轨上去。  ",
            "article_url": "",
            "original_pictures": "无",
            "retweet_pictures": null,
            "original": true,
            "video_url": "无",
            "publish_place": "无",
            "publish_time": "2024-11-06 16:58",
            "publish_tool": "微博网页版",
            "up_num": 1325,
            "retweet_num": 39,
            "comment_num": 43
        },
        {
            "id": "OEXPPBg1B",
            "user_id": "",
            "content": "今天的美国大选只可能有两个结果。1、川普当选。2、川普说哈里斯舞弊。  ",
            "article_url": "",
            "original_pictures": "无",
            "retweet_pictures": null,
            "original": true,
            "video_url": "无",
            "publish_place": "无",
            "publish_time": "2024-11-06 08:37",
            "publish_tool": "微博网页版",
            "up_num": 424,
            "retweet_num": 3,
            "comment_num": 12
        },
        {
            "id": "OETL8ug9o",
            "user_id": "",
            "content": "世界是一个巨大的瑞士卷。有的人分到了瑞士，有的人分到了卷。  ",
            "article_url": "",
            "original_pictures": "无",
            "retweet_pictures": null,
            "original": true,
            "video_url": "无",
            "publish_place": "无",
            "publish_time": "2024-11-05 22:15",
            "publish_tool": "微博网页版",
            "up_num": 21891,
            "retweet_num": 18896,
            "comment_num": 891
        },
        {
            "id": "OERwilBVd",
            "user_id": "",
            "content": "你认为哪一方的责任更大？ 你认为哪一方的责任更大？ （肯定有取样偏差，投票结果仅供参考）  ",
            "article_url": "",
            "original_pictures": "无",
            "retweet_pictures": null,
            "original": true,
            "video_url": "无",
            "publish_place": "无",
            "publish_time": "2024-11-05 16:33",
            "publish_tool": "微博网页版",
            "up_num": 706,
            "retweet_num": 4,
            "comment_num": 12
        },
        {
            "id": "OEJgK8P6z",
            "user_id": "",
            "content": "刚知道今天的热搜是瑞士卷。#瑞士卷怎么分#  这要问问两年前上海那个居委会，分瑞士卷，它们最专业了。上海一#居委会给居民发泡面居委干部吃瑞士卷##官方回应给居民发泡面居委干部吃瑞士卷#  ",
            "article_url": "",
            "original_pictures": "无",
            "retweet_pictures": null,
            "original": true,
            "video_url": "无",
            "publish_place": "无",
            "publish_time": "2024-11-04 19:32",
            "publish_tool": "微博网页版",
            "up_num": 11858,
            "retweet_num": 5054,
            "comment_num": 177
        },
        {
            "id": "OEJaF8bwf",
            "user_id": "",
            "content": "刚知道美国那只网红松鼠被人举报被政府相关部门入室消……入室杀掉的事情。看了下广场上兴奋地喊着“鼠命贵”“一只松鼠影响美国大选”“川普绝杀”的怔能量们，两年前它们不会为那只柯基那条萨摩耶和那些猫发半点声音。每个尊重生命的人都值得尊重。这些人不在其中。  ",
            "article_url": "",
            "original_pictures": "无",
            "retweet_pictures": null,
            "original": true,
            "video_url": "无",
            "publish_place": "无",
            "publish_time": "2024-11-04 19:18",
            "publish_tool": "微博网页版",
            "up_num": 374,
            "retweet_num": 20,
            "comment_num": 14
        },
        {
            "id": "OEBhqg0Wt",
            "user_id": "",
            "content": "今天涟水专科对王的处罚通知、阿里的道歉，其实依然是含糊的。最大的含糊之处在于：它们仅仅指出了王对姜萍的预赛答题是有参与的，但参与到怎样的程度，却没有更多说明。姜萍究竟是某些人口中的”数学白痴“，还是说，虽然能力距离全球第12相去甚远，但她其实也有至少超过同辈的数学能力和热情？“数学白痴”和“数学天才”之间，有没有可能存在一个中间地带？根据极昼工作室的报道 http://t.cn/A6QteyQn （独立第三方的报道在我看来是有更多可信度的，包括采访到的姜萍的同学，因为没有利益关联，他们没有圆谎的动机，所以我觉得可能更接近真实情况），王确实经常一对一辅导姜，而姜也确实对数学很感兴趣，她的数学进步也的确很快。如果姜萍真的是完全懵懂的”数学白痴“，仅仅只是王闰秋随便找到的傀儡，那倒也算了，这”只是“一个集体造假被戳穿的故事，一个最被动的工具人成为替罪羊的故事（虽然也很惨）。但是，如果是后者（当王向姜萍发出邀请，姜萍的第一反应是”我也配？“——这话也的确更像是后一种情况，真的数学白痴只会不明所以”阿里巴巴数学竞赛是啥“，而不会产生这种”自己的努力被过度褒奖“的不配得感的反应），那么王的做法不但利用了姜萍这个人，还剥削了她对数学的质朴热情。其实这种可能也可以在一定程度上解释为什么央视没有在拍摄中及时发现问题（假设这国家电视台还有起码的事实核查的职业道德）：因为姜萍虽然在预赛中获得了王的帮助，但她对数学的热爱，乃至具备一定的数学功底，这些都是事实。我宁愿前一种可能才是真的。如果姜萍是因为自己真实的热爱（和天赋）进入王闰秋的视野，成为教师、资本和官媒这些权力上位者轮番利用榨取的目标，最终被献祭到舆论的火堆上，成为整个事件中唯一的挡箭牌，学历和性别歧视的双重牺牲品……无法想象这是怎样的惨痛和不公。还有一点，在质疑声浪里，无论阿里还是央视，它们和姜萍的利益是大相径庭的：前者需要证明姜萍的能力真的达到预赛全球前12，否则这个case就是造假丑闻，这对于阿里和央视这样的机构来说依然都是不可接受的；但对姜萍来说，其实她只要证明自己的数学能力明显高出同辈人，哪怕私下沟通题目依然是违规的，哪怕自证并非她的义务，她都可以少受很多类似“数学白痴”的攻击，而数学的自证其实是相对可操作的。但即便她真的有这个能力和意愿，那些由成年人组成的老师、资本、官媒，也不会给她这个自辩自证的机会，它们只会打着“保护未成年人”的幌子让她封口。虽然在很多人眼里这件事已经尘埃落定，我还是希望有一天有记者能找到姜萍。也许在她的角度，这会是一个完全不一样的故事。#姜某数学竞赛系老师提供帮助##王某某为姜萍竞赛提供帮助被处分##姜萍事件原委##阿里巴巴全球数学竞赛获奖名单公布##阿里巴巴就姜萍事件道歉# ",
            "article_url": "",
            "original_pictures": "无",
            "retweet_pictures": null,
            "original": true,
            "video_url": "无",
            "publish_place": "无",
            "publish_time": "2024-11-03 23:12",
            "publish_tool": "微博网页版",
            "up_num": 915,
            "retweet_num": 248,
            "comment_num": 41
        },
        {
            "id": "OEx4qxXu5",
            "user_id": "",
            "content": "姜萍得到了什么好处？什么都没有。她自始至终都是别人的工具。数学老师为了自己的利益物色了姜萍，作为给自己增加答题时间的工具，他只是利用了姜萍对数学的兴趣，和爱才没有一毛钱的关系，被阿里官方选中出圈完全是个意外；阿里巴巴为了自己的赛事ip，不顾赛事本身巨大的、任何人都可以利用并且很可能此前已经被广为利用的规则漏洞，把姜萍当成宣传的工具；央视为了宣传中考分流，为条件差的学生提供“正能量”，不加事实核查就把姜萍当成正面典型；整个事件就是各路具有各种主导地位的成年人将一个对数学真的有兴趣的中专女生当成工具、素材，用完即弃，在质疑声中长时间躲在后面保持沉默，让一个未成年人独自承受炮火和嘲笑的过程。如果不是不为人知的力量的推动，丝毫不用怀疑这件事最后连道歉和结果都不会有，唯一结果就是姜萍一个人被各路势力吃干抹净。整个事件几乎没有一个成年人在公众记忆中留下自己的名字（还有多少人记得男数学老师叫王润秋？）。这个事件人称“姜萍事件”。我呸。补充：在被包装出来的“数学天才”和被极尽嘲讽的“数学白痴”之间，其实完全可能存在一个中间地带。但在各利益方的合力阻拦下，无论是姜萍自己还是外界想要证明这一点，都已经基本不可能了。👉http://t.cn/A6nmeVw4#姜某数学竞赛系老师提供帮助##王某某为姜萍竞赛提供帮助被处分##姜萍事件原委##阿里巴巴全球数学竞赛获奖名单公布##阿里巴巴就姜萍事件道歉# ",
            "article_url": "",
            "original_pictures": "无",
            "retweet_pictures": null,
            "original": true,
            "video_url": "无",
            "publish_place": "无",
            "publish_time": "2024-11-03 12:29",
            "publish_tool": "无",
            "up_num": 74530,
            "retweet_num": 9758,
            "comment_num": 1079
        },
        {
            "id": "OEqjx7A7U",
            "user_id": "",
            "content": "美国大选的两派对话可以概括如下：“你难道不知道川普是什么样的人吗？”“我难道不知道川普是什么样的人吗？”  ",
            "article_url": "",
            "original_pictures": "无",
            "retweet_pictures": null,
            "original": true,
            "video_url": "无",
            "publish_place": "无",
            "publish_time": "2024-11-02 19:17",
            "publish_tool": "无",
            "up_num": 37,
            "retweet_num": 0,
            "comment_num": 2
        },
        {
            "id": "OE9n3nlTu",
            "user_id": "",
            "content": "万圣节结束了。此地再一次遥遥领先：此地的万圣节一年前就结束了。  ",
            "article_url": "",
            "original_pictures": "无",
            "retweet_pictures": null,
            "original": true,
            "video_url": "无",
            "publish_place": "无",
            "publish_time": "2024-11-01 00:09",
            "publish_tool": "无",
            "up_num": 344,
            "retweet_num": 16,
            "comment_num": 11
        },
        {
            "id": "OE6esdGu1",
            "user_id": "",
            "content": "南昌工学院里那个行凶的穿连帽衫的男的坐在被害者前面的照片，马上会成为incel新的精神图腾。  ",
            "article_url": "",
            "original_pictures": "无",
            "retweet_pictures": null,
            "original": true,
            "video_url": "无",
            "publish_place": "无",
            "publish_time": "2024-10-31 16:10",
            "publish_tool": "微博网页版",
            "up_num": 814,
            "retweet_num": 42,
            "comment_num": 28
        },
        {
            "id": "ODYRTwM3Y",
            "user_id": "",
            "content": "只喝无糖饮料的人聚集在一起，就有了Wu-Tang Clan。  ",
            "article_url": "",
            "original_pictures": "无",
            "retweet_pictures": null,
            "original": true,
            "video_url": "无",
            "publish_place": "无",
            "publish_time": "2024-10-30 21:25",
            "publish_tool": "微博网页版",
            "up_num": 34,
            "retweet_num": 2,
            "comment_num": 5
        },
        {
            "id": "ODYbJy5lL",
            "user_id": "",
            "content": "今日tag见闻#报告称老人是提升生育意愿关键因素# #老人该不该帮儿女带孩子# #专家称孕育会使女性变得更聪明# #直面不想生不敢生不能生# 他们发现了关键的问题，但还没有发现问题的关键。  ",
            "article_url": "",
            "original_pictures": "无",
            "retweet_pictures": null,
            "original": true,
            "video_url": "无",
            "publish_place": "无",
            "publish_time": "2024-10-30 19:41",
            "publish_tool": "微博网页版",
            "up_num": 152,
            "retweet_num": 11,
            "comment_num": 10
        },
        {
            "id": "ODQ0ZFklG",
            "user_id": "",
            "content": "陈思诚现在应该一边在疯狂拉片《因果报应》，一边给肖央打电话，一边叫版权团队星夜赶往印度。陈思诚激动地对他的下一部新片说：“在我的世界里，你已经杀青了！”  ",
            "article_url": "",
            "original_pictures": "无",
            "retweet_pictures": null,
            "original": true,
            "video_url": "无",
            "publish_place": "无",
            "publish_time": "2024-10-29 22:53",
            "publish_tool": "微博网页版",
            "up_num": 29,
            "retweet_num": 1,
            "comment_num": 2
        },
        {
            "id": "ODPWBzOoz",
            "user_id": "",
            "content": "陈思诚现在应该在拉片《因果报应》。  ",
            "article_url": "",
            "original_pictures": "无",
            "retweet_pictures": null,
            "original": true,
            "video_url": "无",
            "publish_place": "无",
            "publish_time": "2024-10-29 22:42",
            "publish_tool": "微博网页版",
            "up_num": 14,
            "retweet_num": 0,
            "comment_num": 2
        },
        {
            "id": "ODORjaGJq",
            "user_id": "",
            "content": "以后有啥想看的片子要尽快看，你永远不知道明天和意外哪个先来。比如我一直拖着没看很想看的《晒后假日》，现在意外看了一个访谈cut就已经对保罗麦斯卡好感清零了。  ",
            "article_url": "",
            "original_pictures": "无",
            "retweet_pictures": null,
            "original": true,
            "video_url": "无",
            "publish_place": "无",
            "publish_time": "2024-10-29 19:56",
            "publish_tool": "微博网页版",
            "up_num": 27,
            "retweet_num": 0,
            "comment_num": 10
        },
        {
            "id": "ODG6FlqGk",
            "user_id": "",
            "content": "据说那个拿下持刀凶徒的小学棒球教练，开始上前是以为有家长在打小孩。能为这种很多人眼里的“家务事”“小事”而上前的人，果然也是有大勇的人。  ",
            "article_url": "",
            "original_pictures": "无",
            "retweet_pictures": null,
            "original": true,
            "video_url": "无",
            "publish_place": "无",
            "publish_time": "2024-10-28 21:39",
            "publish_tool": "微博网页版",
            "up_num": 309,
            "retweet_num": 24,
            "comment_num": 2
        },
        {
            "id": "ODELnCZt2",
            "user_id": "",
            "content": "说实话我现在看到通报里的“无生命危险”五个字的时候已经不是“放下心来”而是反而会产生一种幻痛。因为按照现在最常见的通报逻辑，这极简的五个字背后往往可能代表着存在严重的局部创伤和昏迷。  ",
            "article_url": "",
            "original_pictures": "无",
            "retweet_pictures": null,
            "original": true,
            "video_url": "无",
            "publish_place": "无",
            "publish_time": "2024-10-28 18:14",
            "publish_tool": "微博网页版",
            "up_num": 639,
            "retweet_num": 64,
            "comment_num": 21
        },
        {
            "id": "ODx249VZe",
            "user_id": "",
            "content": "学过中学数学的都知道，cos和sin有密切的关系，可见cos是有原罪的。  ",
            "article_url": "",
            "original_pictures": "无",
            "retweet_pictures": null,
            "original": true,
            "video_url": "无",
            "publish_place": "无",
            "publish_time": "2024-10-27 22:33",
            "publish_tool": "微博网页版",
            "up_num": 339,
            "retweet_num": 105,
            "comment_num": 16
        },
        {
            "id": "ODvYxCHsw",
            "user_id": "",
            "content": "试试看两年前日本的这个万圣节视频链接还活着吗。佳能，感动常在。安利摄的微博视频  ",
            "article_url": "",
            "original_pictures": "无",
            "retweet_pictures": null,
            "original": true,
            "video_url": "无",
            "publish_place": "无",
            "publish_time": "2024-10-27 19:52",
            "publish_tool": "微博视频号",
            "up_num": 139,
            "retweet_num": 20,
            "comment_num": 7
        },
        {
            "id": "OD970fzn4",
            "user_id": "",
            "content": "刚才去个还没开完全门的商场，在里面路过一个玻璃侧门，一位女士从外面想进来却发现门锁了。我隔着门缝告诉她“不能从这一侧打开”，感觉自己cos了宫崎英高。  ",
            "article_url": "",
            "original_pictures": "无",
            "retweet_pictures": null,
            "original": true,
            "video_url": "无",
            "publish_place": "无",
            "publish_time": "2024-10-25 09:39",
            "publish_tool": "无",
            "up_num": 28,
            "retweet_num": 0,
            "comment_num": 3
        }
    ]
}